{
  "gm_id": 8,
  "gm_name": "Zach",
  "career_summary": {
    "total_picks_made": 269,
    "sum_total_pvdre": -3916.09,
    "average_pvdre_per_pick": -14.56,
    "total_hits": 103,
    "total_misses": 166,
    "career_hit_rate_percentage": 38.3
  },
  "round_efficiency": [
    {
      "round": 1.0,
      "picks_count": 16.0,
      "average_pvdre": -16.79,
      "total_pvdre": -268.63
    },
    {
      "round": 2.0,
      "picks_count": 16.0,
      "average_pvdre": -24.69,
      "total_pvdre": -395.03
    },
    {
      "round": 3.0,
      "picks_count": 16.0,
      "average_pvdre": -45.08,
      "total_pvdre": -721.2
    },
    {
      "round": 4.0,
      "picks_count": 16.0,
      "average_pvdre": -26.9,
      "total_pvdre": -430.39
    },
    {
      "round": 5.0,
      "picks_count": 16.0,
      "average_pvdre": -28.66,
      "total_pvdre": -458.63
    },
    {
      "round": 6.0,
      "picks_count": 16.0,
      "average_pvdre": -23.5,
      "total_pvdre": -376.05
    },
    {
      "round": 7.0,
      "picks_count": 16.0,
      "average_pvdre": -18.18,
      "total_pvdre": -290.88
    },
    {
      "round": 8.0,
      "picks_count": 16.0,
      "average_pvdre": -16.32,
      "total_pvdre": -261.08
    },
    {
      "round": 9.0,
      "picks_count": 16.0,
      "average_pvdre": -18.18,
      "total_pvdre": -290.92
    },
    {
      "round": 10.0,
      "picks_count": 16.0,
      "average_pvdre": -18.12,
      "total_pvdre": -289.86
    },
    {
      "round": 11.0,
      "picks_count": 16.0,
      "average_pvdre": -11.27,
      "total_pvdre": -180.36
    },
    {
      "round": 12.0,
      "picks_count": 16.0,
      "average_pvdre": 1.39,
      "total_pvdre": 22.16
    },
    {
      "round": 13.0,
      "picks_count": 16.0,
      "average_pvdre": -14.91,
      "total_pvdre": -238.55
    },
    {
      "round": 14.0,
      "picks_count": 16.0,
      "average_pvdre": 9.17,
      "total_pvdre": 146.79
    },
    {
      "round": 15.0,
      "picks_count": 16.0,
      "average_pvdre": 13.51,
      "total_pvdre": 216.09
    },
    {
      "round": 16.0,
      "picks_count": 15.0,
      "average_pvdre": 13.66,
      "total_pvdre": 204.93
    },
    {
      "round": 17.0,
      "picks_count": 14.0,
      "average_pvdre": -21.75,
      "total_pvdre": -304.48
    }
  ],
  "best_picks": [
    {
      "season_id": 2012,
      "pick_overall": 67,
      "draft_id": 564,
      "round": 7,
      "pick_in_round": 7,
      "player_id": 14385,
      "player_name": "Doug Martin",
      "player_position": "RB",
      "nfl_team_id": "TB",
      "nfl_team_name": "Tampa Bay Buccaneers",
      "fantasy_team_id": 38,
      "fantasy_team_name": "Mouse Rat",
      "gm_id": 8,
      "gm_name": "Zach",
      "league_positional_draft_rank": 27,
      "overall_adp_rank": 25.0,
      "market_positional_adp_rank": 14.0,
      "overall_reach_steal_value": 42.0,
      "actual_total_fantasy_points_season": 262.6,
      "fantasy_points_per_game_season": 16.4,
      "actual_positional_finish_rank": 2.0,
      "expected_points_for_league_draft_rank_smoothed": 117.93,
      "pvdre_points_vs_league_draft_rank_exp": 144.67,
      "rank_diff_vs_league_draft_rank": 25.0,
      "pvdre_numeric_for_league_avg": 144.67,
      "pvdre_numeric": 144.67,
      "pvdre_for_sort": 144.67
    },
    {
      "season_id": 2009,
      "pick_overall": 114,
      "draft_id": 114,
      "round": 12,
      "pick_in_round": 4,
      "player_id": 9528,
      "player_name": "Brett Favre",
      "player_position": "QB",
      "nfl_team_id": "MIN",
      "nfl_team_name": "Minnesota Vikings",
      "fantasy_team_id": 8,
      "fantasy_team_name": "Free Agent Schaefer Slayer",
      "gm_id": 8,
      "gm_name": "Zach",
      "league_positional_draft_rank": 19,
      "overall_adp_rank": 99.0,
      "market_positional_adp_rank": 13.0,
      "overall_reach_steal_value": 15.0,
      "actual_total_fantasy_points_season": 283.1,
      "fantasy_points_per_game_season": 17.7,
      "actual_positional_finish_rank": 3.0,
      "expected_points_for_league_draft_rank_smoothed": 173.48,
      "pvdre_points_vs_league_draft_rank_exp": 109.62,
      "rank_diff_vs_league_draft_rank": 16.0,
      "pvdre_numeric_for_league_avg": 109.62,
      "pvdre_numeric": 109.62,
      "pvdre_for_sort": 109.62
    },
    {
      "season_id": 2011,
      "pick_overall": 124,
      "draft_id": 452,
      "round": 13,
      "pick_in_round": 4,
      "player_id": 4932,
      "player_name": "Eli Manning",
      "player_position": "QB",
      "nfl_team_id": "NYG",
      "nfl_team_name": "New York Giants",
      "fantasy_team_id": 28,
      "fantasy_team_name": "Gabby's Gobblers",
      "gm_id": 8,
      "gm_name": "Zach",
      "league_positional_draft_rank": 19,
      "overall_adp_rank": 95.0,
      "market_positional_adp_rank": 13.0,
      "overall_reach_steal_value": 29.0,
      "actual_total_fantasy_points_season": 279.9,
      "fantasy_points_per_game_season": 17.5,
      "actual_positional_finish_rank": 6.0,
      "expected_points_for_league_draft_rank_smoothed": 171.42,
      "pvdre_points_vs_league_draft_rank_exp": 108.48,
      "rank_diff_vs_league_draft_rank": 13.0,
      "pvdre_numeric_for_league_avg": 108.48,
      "pvdre_numeric": 108.48,
      "pvdre_for_sort": 108.48
    },
    {
      "season_id": 2011,
      "pick_overall": 117,
      "draft_id": 445,
      "round": 12,
      "pick_in_round": 7,
      "player_id": 371,
      "player_name": "Michael Bush",
      "player_position": "RB",
      "nfl_team_id": "LV",
      "nfl_team_name": "Las Vegas Raiders",
      "fantasy_team_id": 28,
      "fantasy_team_name": "Gabby's Gobblers",
      "gm_id": 8,
      "gm_name": "Zach",
      "league_positional_draft_rank": 41,
      "overall_adp_rank": 106.0,
      "market_positional_adp_rank": 39.0,
      "overall_reach_steal_value": 11.0,
      "actual_total_fantasy_points_season": 185.5,
      "fantasy_points_per_game_season": 11.6,
      "actual_positional_finish_rank": 9.0,
      "expected_points_for_league_draft_rank_smoothed": 86.42,
      "pvdre_points_vs_league_draft_rank_exp": 99.08,
      "rank_diff_vs_league_draft_rank": 32.0,
      "pvdre_numeric_for_league_avg": 99.08,
      "pvdre_numeric": 99.08,
      "pvdre_for_sort": 99.08
    },
    {
      "season_id": 2010,
      "pick_overall": 114,
      "draft_id": 283,
      "round": 12,
      "pick_in_round": 4,
      "player_id": 2220,
      "player_name": "Ahmad Bradshaw",
      "player_position": "RB",
      "nfl_team_id": "NYG",
      "nfl_team_name": "New York Giants",
      "fantasy_team_id": 18,
      "fantasy_team_name": "Felix Me!!!!",
      "gm_id": 8,
      "gm_name": "Zach",
      "league_positional_draft_rank": 39,
      "overall_adp_rank": 66.0,
      "market_positional_adp_rank": 27.0,
      "overall_reach_steal_value": 48.0,
      "actual_total_fantasy_points_season": 192.9,
      "fantasy_points_per_game_season": 12.1,
      "actual_positional_finish_rank": 14.0,
      "expected_points_for_league_draft_rank_smoothed": 94.34,
      "pvdre_points_vs_league_draft_rank_exp": 98.56,
      "rank_diff_vs_league_draft_rank": 25.0,
      "pvdre_numeric_for_league_avg": 98.56,
      "pvdre_numeric": 98.56,
      "pvdre_for_sort": 98.56
    }
  ],
  "worst_picks": [
    {
      "season_id": 2016,
      "pick_overall": 1,
      "draft_id": 1178,
      "round": 1,
      "pick_in_round": 1,
      "player_id": 4807,
      "player_name": "Adrian Peterson",
      "player_position": "RB",
      "nfl_team_id": "MIN",
      "nfl_team_name": "Minnesota Vikings",
      "fantasy_team_id": 78,
      "fantasy_team_name": "Tommy Terrific",
      "gm_id": 8,
      "gm_name": "Zach",
      "league_positional_draft_rank": 1,
      "overall_adp_rank": 7.0,
      "market_positional_adp_rank": 4.0,
      "overall_reach_steal_value": -6.0,
      "actual_total_fantasy_points_season": 6.0,
      "fantasy_points_per_game_season": 2.0,
      "actual_positional_finish_rank": 124.0,
      "expected_points_for_league_draft_rank_smoothed": 267.95,
      "pvdre_points_vs_league_draft_rank_exp": -261.95,
      "rank_diff_vs_league_draft_rank": -123.0,
      "pvdre_numeric_for_league_avg": -261.95,
      "pvdre_numeric": -261.95,
      "pvdre_for_sort": -261.95
    },
    {
      "season_id": 2015,
      "pick_overall": 46,
      "draft_id": 1053,
      "round": 5,
      "pick_in_round": 6,
      "player_id": 7328,
      "player_name": "Peyton Manning",
      "player_position": "QB",
      "nfl_team_id": "DEN",
      "nfl_team_name": "Denver Broncos",
      "fantasy_team_id": 68,
      "fantasy_team_name": "Janna Banana",
      "gm_id": 8,
      "gm_name": "Zach",
      "league_positional_draft_rank": 4,
      "overall_adp_rank": 45.0,
      "market_positional_adp_rank": 3.0,
      "overall_reach_steal_value": 1.0,
      "actual_total_fantasy_points_season": 91.4,
      "fantasy_points_per_game_season": 9.1,
      "actual_positional_finish_rank": 34.0,
      "expected_points_for_league_draft_rank_smoothed": 332.52,
      "pvdre_points_vs_league_draft_rank_exp": -241.12,
      "rank_diff_vs_league_draft_rank": -30.0,
      "pvdre_numeric_for_league_avg": -241.12,
      "pvdre_numeric": -241.12,
      "pvdre_for_sort": -241.12
    },
    {
      "season_id": 2016,
      "pick_overall": 21,
      "draft_id": 1198,
      "round": 3,
      "pick_in_round": 1,
      "player_id": 7969,
      "player_name": "Jamaal Charles",
      "player_position": "RB",
      "nfl_team_id": "KC",
      "nfl_team_name": "Kansas City Chiefs",
      "fantasy_team_id": 78,
      "fantasy_team_name": "Tommy Terrific",
      "gm_id": 8,
      "gm_name": "Zach",
      "league_positional_draft_rank": 11,
      "overall_adp_rank": 17.0,
      "market_positional_adp_rank": 8.0,
      "overall_reach_steal_value": 4.0,
      "actual_total_fantasy_points_season": 11.4,
      "fantasy_points_per_game_season": 3.8,
      "actual_positional_finish_rank": 109.0,
      "expected_points_for_league_draft_rank_smoothed": 200.67,
      "pvdre_points_vs_league_draft_rank_exp": -189.27,
      "rank_diff_vs_league_draft_rank": -98.0,
      "pvdre_numeric_for_league_avg": -189.27,
      "pvdre_numeric": -189.27,
      "pvdre_for_sort": -189.27
    },
    {
      "season_id": 2024,
      "pick_overall": 17,
      "draft_id": 2588,
      "round": 2,
      "pick_in_round": 5,
      "player_id": 21696,
      "player_name": "Travis Etienne Jr.",
      "player_position": "RB",
      "nfl_team_id": "JAX",
      "nfl_team_name": "Jacksonville Jaguars",
      "fantasy_team_id": 160,
      "fantasy_team_name": "MouseRat  FC",
      "gm_id": 8,
      "gm_name": "Zach",
      "league_positional_draft_rank": 9,
      "overall_adp_rank": 17.0,
      "market_positional_adp_rank": 8.0,
      "overall_reach_steal_value": 0.0,
      "actual_total_fantasy_points_season": 91.2,
      "fantasy_points_per_game_season": 6.1,
      "actual_positional_finish_rank": 39.0,
      "expected_points_for_league_draft_rank_smoothed": 235.31,
      "pvdre_points_vs_league_draft_rank_exp": -144.11,
      "rank_diff_vs_league_draft_rank": -30.0,
      "pvdre_numeric_for_league_avg": -144.11,
      "pvdre_numeric": -144.11,
      "pvdre_for_sort": -144.11
    },
    {
      "season_id": 2020,
      "pick_overall": 25,
      "draft_id": 1882,
      "round": 3,
      "pick_in_round": 5,
      "player_id": 18977,
      "player_name": "Kenny Golladay",
      "player_position": "WR",
      "nfl_team_id": "DET",
      "nfl_team_name": "Detroit Lions",
      "fantasy_team_id": 118,
      "fantasy_team_name": "MouseRat  FC",
      "gm_id": 8,
      "gm_name": "Zach",
      "league_positional_draft_rank": 7,
      "overall_adp_rank": 26.0,
      "market_positional_adp_rank": 7.0,
      "overall_reach_steal_value": -1.0,
      "actual_total_fantasy_points_season": 45.8,
      "fantasy_points_per_game_season": 9.2,
      "actual_positional_finish_rank": 99.0,
      "expected_points_for_league_draft_rank_smoothed": 183.02,
      "pvdre_points_vs_league_draft_rank_exp": -137.22,
      "rank_diff_vs_league_draft_rank": -92.0,
      "pvdre_numeric_for_league_avg": -137.22,
      "pvdre_numeric": -137.22,
      "pvdre_for_sort": -137.22
    }
  ],
  "positional_profile": [
    {
      "position": "DST",
      "picks_count": 17,
      "gm_average_pvdre": -15.05,
      "league_average_pvdre": -15.73,
      "gm_total_pvdre": -255.93
    },
    {
      "position": "K",
      "picks_count": 16,
      "gm_average_pvdre": -22.43,
      "league_average_pvdre": -27.52,
      "gm_total_pvdre": -358.84
    },
    {
      "position": "QB",
      "picks_count": 23,
      "gm_average_pvdre": -8.68,
      "league_average_pvdre": -39.55,
      "gm_total_pvdre": -199.74
    },
    {
      "position": "RB",
      "picks_count": 93,
      "gm_average_pvdre": -14.49,
      "league_average_pvdre": -18.28,
      "gm_total_pvdre": -1347.23
    },
    {
      "position": "TE",
      "picks_count": 25,
      "gm_average_pvdre": -10.66,
      "league_average_pvdre": -21.77,
      "gm_total_pvdre": -266.55
    },
    {
      "position": "WR",
      "picks_count": 95,
      "gm_average_pvdre": -15.66,
      "league_average_pvdre": -19.52,
      "gm_total_pvdre": -1487.8
    }
  ],
  "draft_strategy_summary": "Analysis of drafting tendencies compared to league averages."
}